actor.py
misc.py
activity_tools/actor.py
activity_tools/crypto.py
activity_tools/headers.py
activity_tools/inbox.py
activity_tools/misc.py
activity_tools/objects.py
activity_tools-0.0.8.dist-info/LICENSE
activity_tools-0.0.8.dist-info/METADATA
activity_tools-0.0.8.dist-info/WHEEL
activity_tools-0.0.8.dist-info/top_level.txt
activity_tools-0.0.8.dist-info/RECORD
