Metadata-Version: 2.1
Name: activity-tools
Version: 0.0.8
Summary: ActivityPub building blocks for Python
Author: Stefan Berggren
Author-email: pypi+activity-tools@enesge.eu
Maintainer: Stefan Berggren
Maintainer-email: pypi+activity-tools@enesge.eu
License: MIT License
Project-URL: homepage, https://github.com/nsg/activity-tools
Project-URL: documentation, https://github.com/nsg/activity-tools
Project-URL: repository, https://github.com/nsg/activity-tools.git
Project-URL: changelog, https://github.com/nsg/activity-tools/blob/master/CHANGELOG.md
Classifier: Programming Language :: Python :: 3
Classifier: License :: OSI Approved :: MIT License
Classifier: Operating System :: OS Independent
Requires-Python: >=3.6
License-File: LICENSE
Requires-Dist: cryptography (>=39.0.0)
Requires-Dist: requests (>=2.28.0)
